excelkit/__init__.py
excelkit/bin/__init__.py
excelkit/bin/_build.py
excelkit/bin/_concat.py
excelkit/bin/_parse.py
excelkit/bin/main.py
excelkit/core/__init__.py
excelkit/core/build.py
excelkit/core/concat.py
excelkit/core/merge.py
excelkit/core/parse.py
excelkit/util/__init__.py
excelkit/util/reformat.py
excelkit/util/styles.py
excelkit/version/version.json
excelkit-1.0.0.dist-info/METADATA
excelkit-1.0.0.dist-info/WHEEL
excelkit-1.0.0.dist-info/entry_points.txt
excelkit-1.0.0.dist-info/top_level.txt
excelkit-1.0.0.dist-info/RECORD
